{
  "$schema": "https://ui.shadcn.com/schema/registry-item.json",
  "name": "dialog",
  "type": "registry:ui",
  "dependencies": [
    "@ark-ui/react",
    "tailwind-variants",
    "lucide-react"
  ],
  "registryDependencies": [
    "https://shark.vini.one/r/button.json"
  ],
  "files": [
    {
      "path": "registry/react/components/dialog.tsx",
      "content": "import { Dialog as ArkDialog } from \"@ark-ui/react/dialog\";\nimport { Portal } from \"@ark-ui/react/portal\";\nimport { X } from \"lucide-react\";\nimport type React from \"react\";\nimport { tv, type VariantProps } from \"tailwind-variants\";\nimport { cn } from \"@/lib/utils\";\nimport { Button } from \"@/registry/react/components/button\";\n\nexport const Dialog = (props: React.ComponentProps<typeof ArkDialog.Root>) => {\n  const { lazyMount = true, unmountOnExit = true, ...rest } = props;\n\n  return (\n    <ArkDialog.Root\n      lazyMount={lazyMount}\n      unmountOnExit={unmountOnExit}\n      {...rest}\n    />\n  );\n};\n\nexport const DialogTrigger = (\n  props: React.ComponentProps<typeof ArkDialog.Trigger>\n) => <ArkDialog.Trigger {...props} />;\n\nexport const dialogBackdropVariants = tv({\n  base: [\n    \"z-50\",\n    \"fixed inset-0\",\n    \"bg-background/50 backdrop-blur-xs\",\n    \"data-[state=closed]:animate-out data-[state=open]:animate-in\",\n    \"data-[state=closed]:fade-out-0 data-[state=open]:fade-in-0\",\n  ],\n});\n\nexport const DialogBackdrop = (\n  props: React.ComponentProps<typeof ArkDialog.Backdrop>\n) => {\n  const { className, ...rest } = props;\n\n  return (\n    <ArkDialog.Backdrop\n      className={cn(dialogBackdropVariants(), className)}\n      {...rest}\n    />\n  );\n};\n\nexport const dialogContentVariants = tv({\n  base: [\n    \"relative\",\n    \"z-50\",\n    \"-translate-x-1/2 -translate-y-1/2 fixed top-1/2 left-1/2\",\n    \"flex flex-col gap-4\",\n    \"bg-background\",\n    \"w-full max-w-[calc(100%-2rem)] sm:max-w-lg\",\n    \"rounded-lg border shadow-lg\",\n    \"focus:outline-none focus:ring-0\",\n    \"data-[state=closed]:animate-out data-[state=open]:animate-in\",\n    \"data-[state=open]:fade-in-0 data-[state=closed]:fade-out-0\",\n    \"data-[state=open]:zoom-in-95 data-[state=closed]:zoom-out-95\",\n  ],\n  variants: {\n    size: {\n      sm: [\"max-w-sm\"],\n      md: [\"max-w-md\"],\n      lg: [\"max-w-lg\"],\n      xl: [\"max-w-xl\"],\n      \"2xl\": [\"max-w-2xl\"],\n      \"3xl\": [\"max-w-3xl\"],\n      \"4xl\": [\"max-w-4xl\"],\n      \"5xl\": [\"max-w-5xl\"],\n      \"6xl\": [\"max-w-6xl\"],\n      \"7xl\": [\"max-w-7xl\"],\n      \"8xl\": [\"max-w-8xl\"],\n      fullscreen: [\"size-full\"],\n    },\n  },\n  defaultVariants: {\n    size: \"md\",\n  },\n});\n\ninterface DialogContentProps\n  extends React.ComponentProps<typeof ArkDialog.Content>,\n    VariantProps<typeof dialogContentVariants> {\n  /**\n   * Show close button at the top right corner\n   *\n   * @default true\n   */\n  showCloseButton?: boolean;\n}\n\nexport const DialogContent = (props: DialogContentProps) => {\n  const {\n    showCloseButton = true,\n    className,\n    size = \"md\",\n    children,\n    ...rest\n  } = props;\n\n  return (\n    <Portal>\n      <DialogBackdrop />\n\n      <ArkDialog.Positioner>\n        <ArkDialog.Content\n          className={cn(dialogContentVariants({ size }), className)}\n          {...rest}\n        >\n          {children}\n\n          {showCloseButton && (\n            <DialogClose asChild>\n              <Button\n                className=\"absolute top-4 right-4 size-8 opacity-70 hover:opacity-100\"\n                size=\"icon-md\"\n                variant=\"ghost\"\n              >\n                <X />\n\n                <span className=\"sr-only\">Close</span>\n              </Button>\n            </DialogClose>\n          )}\n        </ArkDialog.Content>\n      </ArkDialog.Positioner>\n    </Portal>\n  );\n};\n\nexport const DialogBody = (props: React.ComponentProps<\"div\">) => {\n  const { className, ...rest } = props;\n\n  return (\n    <div\n      className={cn(\"flex-1 overflow-auto p-6\", className)}\n      data-part=\"body\"\n      {...rest}\n    />\n  );\n};\n\ninterface DialogHeaderProps extends React.ComponentProps<\"div\"> {\n  /**\n   * The title of the dialog\n   */\n  title?: string;\n  /**\n   * The description of the dialog\n   */\n  description?: string;\n}\n\nexport const DialogHeader = (props: DialogHeaderProps) => {\n  const { className, title, description, children, ...rest } = props;\n\n  return (\n    <div\n      className={cn(\"flex flex-col gap-2 p-6 pb-0\", className)}\n      data-part=\"header\"\n      data-scope=\"dialog\"\n      {...rest}\n    >\n      {title && <DialogTitle>{title}</DialogTitle>}\n      {description && <DialogDescription>{description}</DialogDescription>}\n      {!title && typeof children === \"string\" ? (\n        <DialogTitle>{children}</DialogTitle>\n      ) : (\n        children\n      )}\n    </div>\n  );\n};\n\nexport const DialogTitle = (\n  props: React.ComponentProps<typeof ArkDialog.Title>\n) => {\n  const { className, ...rest } = props;\n\n  return (\n    <ArkDialog.Title\n      className={cn(\n        \"font-semibold text-base leading-none tracking-tight\",\n        className\n      )}\n      {...rest}\n    />\n  );\n};\n\nexport const DialogDescription = (\n  props: React.ComponentProps<typeof ArkDialog.Description>\n) => {\n  const { className, ...rest } = props;\n\n  return (\n    <ArkDialog.Description\n      className={cn(\"text-muted-foreground text-sm\", className)}\n      {...rest}\n    />\n  );\n};\n\nexport const DialogClose = (\n  props: React.ComponentProps<typeof ArkDialog.CloseTrigger>\n) => <ArkDialog.CloseTrigger asChild {...props} />;\n\nexport const DialogFooter = (props: React.ComponentProps<\"div\">) => {\n  const { className, ...rest } = props;\n\n  return (\n    <div\n      className={cn(\"flex flex-row-reverse gap-2 p-6 pt-0\", className)}\n      data-part=\"footer\"\n      data-scope=\"dialog\"\n      {...rest}\n    />\n  );\n};\n",
      "type": "registry:ui"
    }
  ]
}