{
  "$schema": "https://ui.shadcn.com/schema/registry-item.json",
  "name": "separator",
  "type": "registry:ui",
  "dependencies": ["@ark-ui/react"],
  "files": [
    {
      "path": "registry/react/components/separator.tsx",
      "content": "\"use client\";\n\nimport { ark } from \"@ark-ui/react/factory\";\nimport { cn } from \"@/lib/utils\";\n\ninterface SeparatorProps extends React.ComponentProps<typeof ark.div> {\n  /**\n   * The orientation of the separator.\n   *\n   * @default \"horizontal\"\n   */\n  orientation?: \"horizontal\" | \"vertical\";\n}\n\nexport const Separator = (props: SeparatorProps) => {\n  const { orientation = \"horizontal\", className, ...rest } = props;\n\n  return (\n    <ark.div\n      aria-orientation={orientation}\n      className={cn(\n        \"shrink-0\",\n        \"bg-border\",\n        \"data-[orientation=horizontal]:h-px data-[orientation=horizontal]:w-full\",\n        \"data-[orientation=vertical]:w-px data-[orientation=vertical]:not-[[class^='h-']]:not-[[class*='_h-']]:self-stretch\",\n        className\n      )}\n      data-orientation={orientation}\n      data-slot=\"separator\"\n      role=\"separator\"\n      {...rest}\n    />\n  );\n};\n",
      "type": "registry:ui"
    }
  ]
}
